{
  "items": {
    "https://www.linkedin.com/feed/update/urn:li:share:7464761710386663424": {
      "item_id": "6a15f013b4515f2468e97c0f",
      "slug": "2026-05-26-why-strategic-leaders-must-stay-close-to-the-work-86663424",
      "signature": "ce6a3c6e99f9fe24ad9d28eaad127a10609756c0d803d1edccb773591b4fafc7",
      "published": true
    },
    "https://www.linkedin.com/feed/update/urn:li:share:7465101550017847296": {
      "item_id": "6a16ddbeef0ac832809dbe89",
      "slug": "2026-05-27-not-taking-a-risk-is-a-greater-risk-than-taking-one-17847296",
      "signature": "a7d695dcd7fedd7d3ecad8c79711684188d3e0b41480cc997304ef5ecc1dc73c",
      "published": true
    },
    "https://www.linkedin.com/feed/update/urn:li:share:7465517505990602752": {
      "item_id": "6a1867038c3a0d8f46c7d2d6",
      "slug": "2026-05-28-samsung-ai-boom-widens-memory-chip-profits-and-big-bonuses-90602752",
      "signature": "2863dd31fdefe0c11be74fe1e2c48391d5a27085c9e5b3f7aa33004392560c61",
      "published": true
    },
    "https://www.linkedin.com/feed/update/urn:li:share:7466795473731760129": {
      "item_id": "6a1c81c87c77b9e96df2dbcb",
      "slug": "",
      "signature": "2e7cbd6332e045c9570a424babe7473c6c19581af52bdfb4fb4edff6b081aa15",
      "payload_version": 4,
      "published": true
    },
    "https://www.linkedin.com/feed/update/urn:li:ugcPost:7466911411428872192": {
      "item_id": "6a1d792a5c4648747bab649a",
      "slug": "",
      "signature": "5bd15949085fba3d8c0ff87d04cbbdb39f15041819479deeaa1397c16393a381",
      "payload_version": 7,
      "published": true
    },
    "https://www.linkedin.com/feed/update/urn:li:share:7466930626290589696": {
      "item_id": "6a212dc1423fd8b8301ea808",
      "slug": "",
      "signature": "3c39a0e540b36795396cd6b6408d5e09b0a68f47ea91b08336e5a7931a51d781",
      "payload_version": 7,
      "published": true
    },
    "https://www.linkedin.com/feed/update/urn:li:share:7469029304341868544": {
      "item_id": "6a264d73cce60325275b7f88",
      "slug": "",
      "signature": "b8b351e17f1bde0dcb2d3fd1e5c7d544ba996aa187d0fac593d56948495516b8",
      "payload_version": 7,
      "published": true
    },
    "https://www.linkedin.com/feed/update/urn:li:share:7470130582073819137": {
      "item_id": "6a28ed95ebd45007f3b1cf6e",
      "slug": "",
      "signature": "838f677d30c7ec32c8310edf58bc79cacfbec540e3cd3655a53dec6b8d023426",
      "payload_version": 7,
      "published": true
    },
    "https://www.linkedin.com/feed/update/urn:li:ugcPost:7472986738546864128": {
      "item_id": "6a32bb0a325c071455f44aa7",
      "slug": "",
      "signature": "bb464bebe9d750f9d12ff3ce8a2fbc6332d06bc76305f3f82de901d1cae9514c",
      "payload_version": 7,
      "published": true
    },
    "https://www.linkedin.com/feed/update/urn:li:share:7473391090528759808": {
      "item_id": "6a34d38f5fa5bc2dd8f45ff0",
      "slug": "",
      "signature": "9b75799112d9177cf71062d75b8ce9111f43055b5ff1064ecb67a035a3b66a9c",
      "payload_version": 7,
      "published": true
    },
    "https://www.linkedin.com/feed/update/urn:li:ugcPost:7473979282453671936": {
      "item_id": "6a3774cd1b22f8ccd693c2a7",
      "slug": "",
      "signature": "ffb271e1be35e474e9b34360cdbb78d46cc70dcfaaa77be7d74314305d15a39a",
      "payload_version": 7,
      "published": true
    },
    "https://www.linkedin.com/feed/update/urn:li:share:7473407635833311232": {
      "item_id": "6a38c96842a8c2ca0ba863aa",
      "slug": "",
      "signature": "b579bf7512a4cf4722a541ecf3d859194554ae05c86190023f16799df3356d99",
      "payload_version": 7,
      "published": true
    },
    "https://www.linkedin.com/feed/update/urn:li:share:7473400908199047168": {
      "item_id": "6a3a0c8ca855a46ae4bb5aad",
      "slug": "",
      "signature": "007b0f5c1b38fba2bdc6078158c78a8e0cdfb1d5bf48bf0904eb26149113f4be",
      "payload_version": 7,
      "published": true
    },
    "https://www.linkedin.com/feed/update/urn:li:share:7479928635601096704": {
      "item_id": "6a4c7e4fef0cfb7fd9d1d44b",
      "slug": "",
      "signature": "d58aa407e2e00c3e9683a61f2b334b773a29aaed47d33656a9566acf332407eb",
      "payload_version": 7,
      "published": true
    },
    "https://www.linkedin.com/feed/update/urn:li:share:7480613680913498113": {
      "item_id": "6a4f20aa9b760db4603f1f24",
      "slug": "",
      "signature": "073e34488f6975d53e9d7389ac355170bfcbe631bc921551f3118a8bdee8e2b0",
      "payload_version": 7,
      "published": true
    },
    "https://www.linkedin.com/feed/update/urn:li:share:7480623506196705280": {
      "item_id": "6a5072c1d5bb03a1bb064c1c",
      "slug": "",
      "signature": "5fd715fd1d2529b8678d96c392f7ee5f0d8f33c3fecd4e84048d4004b95d7b8e",
      "payload_version": 7,
      "published": true
    },
    "https://www.linkedin.com/feed/update/urn:li:share:7480625138351235072": {
      "item_id": "6a51bc8afd57bc208338132d",
      "slug": "",
      "signature": "d7c07cbf22314ac56c9e6ed5bd08560753bdcabf45673dd369ab9d50bff99cbc",
      "payload_version": 7,
      "published": true
    },
    "https://www.linkedin.com/feed/update/urn:li:share:7482067127147933696": {
      "item_id": "6a5463cb25db2128980210fc",
      "slug": "",
      "signature": "545883d1729eb5fecf71670d6a32632a7e49b16887bd628bdf7edf837c578786",
      "payload_version": 7,
      "published": true
    },
    "https://www.linkedin.com/feed/update/urn:li:share:7480642503654821888": {
      "item_id": "6a54ea04cbdedb6ea81e0d1e",
      "slug": "",
      "signature": "d0f13cfba2515ff4ad3cf7f07088d45c0c8aa434b4cb743c9d6aa619af40b7a6",
      "payload_version": 7,
      "published": true
    },
    "https://www.linkedin.com/feed/update/urn:li:share:7480652029141504000": {
      "item_id": "6a57012748ceaf2c3a37f921",
      "slug": "",
      "signature": "141224144a3ea299bb853c9b6e236b783cd6e3f93cb483eca6cd31130ba09795",
      "payload_version": 7,
      "published": true
    },
    "https://www.linkedin.com/feed/update/urn:li:share:7482479451486810113": {
      "item_id": "6a585338e5ca177186284f0e",
      "slug": "",
      "signature": "b11dbcf52739b362e0f319d4a0dd21915ffa88b31db9010b5ba53f3210e56676",
      "payload_version": 7,
      "published": true
    },
    "https://www.linkedin.com/feed/update/urn:li:share:7484647868532957184": {
      "item_id": "6a5d9f2d380e411671f8e90d",
      "slug": "",
      "signature": "d20deab00bff75daff998134b2b527867c7630e048ed0ee74235dee57cb75669",
      "payload_version": 7,
      "published": true
    },
    "https://www.linkedin.com/feed/update/urn:li:ugcPost:7484947427934838784": {
      "item_id": "6a5eec96a47352d3b9ae90b9",
      "slug": "",
      "signature": "abdab06e4569f8b512daf453388a1c93071f4dcd0563c8119fdd76055a78ab4f",
      "payload_version": 7,
      "published": true
    },
    "https://www.linkedin.com/feed/update/urn:li:share:7485270806235783168": {
      "item_id": "6a603e1f08781b6996ecb6ee",
      "slug": "",
      "signature": "9bbc5ea8eb73f909f89535c5f8f66d8dcad3ec2532ffd62fe7d6f32ec2d8aabe",
      "payload_version": 7,
      "published": true
    }
  }
}
